timerthread/__init__.py
timerthread/scheduler.py
timerthread/task.py
TimerThread-0.1.1.dist-info/LICENSE
TimerThread-0.1.1.dist-info/METADATA
TimerThread-0.1.1.dist-info/WHEEL
TimerThread-0.1.1.dist-info/top_level.txt
TimerThread-0.1.1.dist-info/RECORD
