Metadata-Version: 2.1
Name: TimerThread
Version: 0.1.1
Summary: A lightweight task scheduling timer
Home-page: https://github.com/yzhang-dev/TimerThread
Author: Yi Zhang
Author-email: yizhang.dev@gmail.com
License: MIT
Download-URL: https://github.com/yzhang-dev/TimerThread
Keywords: timer,background-jobs,background-thread,tasks,background
Platform: UNKNOWN
Classifier: License :: OSI Approved :: MIT License
Classifier: Operating System :: OS Independent
Classifier: Programming Language :: Python :: 3
Classifier: Programming Language :: Python :: 3.7
Requires-Python: >=3.7
